[
  {
    "id": 1,
    "title": "Тяжелая атлетика \n(в Юбилейном мкр.)",
    "category": "Силовой спорт",
    "subcategory": "Тяжелая атлетика",
    "img": "../public/athletics.svg",
    "isFree": true,
    "isFirstFree": false,
    "minAge": 10,
    "maxAge": 18,
    "address": "г. Иркутск, Юбилейный мкр., стр. 49/1",
    "buildingTitle": "ФОК “Юбилейный”",
    "schedule": "Пн, Ср, Пт",
    "timeSlots": ["09:00 - 10:30", "12:00 - 13:30", "18:00 - 19:30"],
    "teacher": "Петрова Елена Александровна",
    "remainingPlaces": "15 из 20",
    "duration": "12 месяцев",
    "description": "Легкая атлетика - олимпийский вид спорта, объединяющий беговые виды, спортивную ходьбу , технические виды (прыжки и метания), многоборья, пробеги (бег по шоссе), кроссы (бег по пересеченной местности).",
    "contents": [
      {
        "title": "Базовый уровень",
        "paragraph": "Базовый уровень сложности первый-второй год обучения, 252 часа.\nОбязательные предметы области (количество часов – 15);\nВариативные предметные области (количество часов −10);\nТеория (количество часов −5);\nПрактика (количество часов − 216);\nСамостоятельная работа (количество часов −2);\nАттестация (количество часов − 4).\nБазовый уровень сложности третий-четвертый год обучения, 416 часов.\nОбязательные предметы области (количество часов − 25);\nВариативные предметные области (количество часов − 15);\nТеория (количество часов − 7);\nПрактика (количество часов − 361);\nСамостоятельная работа (количество часов − 4);\nАттестация (количество часов − 4).\nБазовый уровень сложности пятый-шестой год обучения, 420 часов.\nОбязательные предметы области (количество часов − 27);\nВариативные предметные области (количество часов − 15);\nТеория (количество часов − 8);\nПрактика (количество часов − 360);\nСамостоятельная работа (количество часов − 6);\nАттестация (количество часов − 4)."
      },
      {
        "title": "Углубленный уровень",
        "paragraph": "Углубленный уровень сложности первый-второй год обучения, 504.\nОбязательные предметы области (количество часов − 30);\nВариативные предметные области (количество часов − 20);\nТеория (количество часов − 9);\nПрактика (количество часов − 433);\nСамостоятельная работа (количество часов − 8);\nАттестация (количество часов − 4).\nУглубленный уровень сложности третий-четвертый год обучения, 588 часов.\nОбязательные предметы области (количество часов − 35);\nВариативные предметные области (количество часов − 23);\nТеория (количество часов − 10);\nПрактика (количество часов − 506);\nСамостоятельная работа (количество часов − 10);\nАттестация (количество часов − 4)."
      }
    ]
  },
  {
    "id": 2,
    "title": "Тяжелая атлетика \n(на ул. Боткина)",
    "category": "Силовой спорт",
    "subcategory": "Тяжелая атлетика",
    "img": "",
    "isFree": false,
    "isFirstFree": true,
    "minAge": 10,
    "maxAge": 18,
    "address": "г. Иркутск, Юбилейный мкр., стр. 49/1",
    "buildingTitle": "ФОК “Юбилейный”",
    "schedule": "Пн, Ср, Пт",
    "timeSlots": ["09:00 - 10:30", "12:00 - 13:30"],
    "teacher": "",
    "remainingPlaces": "",
    "duration": "",
    "description": "",
    "contents": []
  },
  {
    "id": 3,
    "title": "Тяжелая атлетика \n(на ул. Норильской)",
    "category": "Силовой спорт",
    "subcategory": "Тяжелая атлетика",
    "img": "",
    "isFree": false,
    "isFirstFree": true,
    "minAge": 10,
    "maxAge": 18,
    "address": "г. Иркутск, Юбилейный мкр., стр. 49/1",
    "buildingTitle": "ФОК “Юбилейный”",
    "schedule": "Пн, Ср, Пт",
    "timeSlots": ["09:00 - 10:30", "12:00 - 13:30", "18:00 - 19:30"],
    "teacher": "",
    "remainingPlaces": "",
    "duration": "",
    "description": "",
    "contents": []
  },
  {
    "id": 4,
    "title": "Пауэрлифтинг",
    "category": "Силовой спорт",
    "subcategory": "Пауэрлифтинг",
    "img": "",
    "isFree": true,
    "isFirstFree": false,
    "minAge": 10,
    "maxAge": 18,
    "address": "г. Иркутск, Юбилейный мкр., стр. 49/1",
    "buildingTitle": "ФОК “Юбилейный”",
    "schedule": "Пн, Ср, Пт",
    "timeSlots": ["09:00 - 10:30", "12:00 - 13:30", "18:00 - 19:30"],
    "teacher": "",
    "remainingPlaces": "",
    "duration": "",
    "description": "",
    "contents": []
  },
  {
    "id": 5,
    "title": "Дзюдо",
    "category": "Единоборства",
    "subcategory": "Дзюдо",
    "img": "",
    "isFree": true,
    "isFirstFree": false,
    "minAge": 6,
    "maxAge": 18,
    "address": "г Иркутск, ул Трудовая, д 115А",
    "buildingTitle": "СК \"Вымпел\"",
    "schedule": "Пн, Ср, Пт",
    "timeSlots": ["09:00 - 10:30", "12:00 - 13:30", "18:00 - 19:30"],
    "teacher": "",
    "remainingPlaces": "",
    "duration": "",
    "description": "",
    "contents": []
  },
  {
    "id": 6,
    "title": "Вольная борьба \n(на ул. Норильская)",
    "category": "Единоборства",
    "subcategory": "Вольная борьба",
    "img": "",
    "isFree": false,
    "isFirstFree": true,
    "minAge": 6,
    "maxAge": 18,
    "address": "г Иркутск, ул Трудовая, д 115А",
    "buildingTitle": "СК \"Вымпел\"",
    "schedule": "Пн, Ср, Пт",
    "timeSlots": ["09:00 - 10:30", "12:00 - 13:30", "18:00 - 19:30"],
    "teacher": "",
    "remainingPlaces": "",
    "duration": "",
    "description": "",
    "contents": []
  }
]